{
"Study Tables":
				[
					"Study Tables",
					"Computer Tables",
					"Study Sets",
					"Laptop Tables",
					"Study Tables For Kids",
					"Solid Wood Study Tables"
					"Study Tables With Storage"
				],
"Study Chairs":
				[
					"Study Chairs",
					"Office Chairs",
					"Ergonomic Study Chairs",
					"Solid Wood Study Chairs",
					"Accent Study Chairs"
				],
"Storage":      
				[
					"Bookshelves",
					"Open Bookshelves",
					"Closed Bookshelves",
					"Wall Shelves"
                ],
"Study Lamps":	
				[
					"Study Lamps"
				],
"Office Furniture": 
				[
					"Office Chairs",
					"Office Tables"
				]

}